odoo/addons/account_move_line_tax_editable/README.rst
odoo/addons/account_move_line_tax_editable/__init__.py
odoo/addons/account_move_line_tax_editable/__manifest__.py
odoo/addons/account_move_line_tax_editable/i18n/account_move_line_tax_editable.pot
odoo/addons/account_move_line_tax_editable/i18n/de.po
odoo/addons/account_move_line_tax_editable/i18n/es.po
odoo/addons/account_move_line_tax_editable/i18n/es_EC.po
odoo/addons/account_move_line_tax_editable/i18n/fr.po
odoo/addons/account_move_line_tax_editable/i18n/hr.po
odoo/addons/account_move_line_tax_editable/i18n/pt.po
odoo/addons/account_move_line_tax_editable/i18n/tr_TR.po
odoo/addons/account_move_line_tax_editable/models/__init__.py
odoo/addons/account_move_line_tax_editable/models/account_move_line.py
odoo/addons/account_move_line_tax_editable/readme/CONTRIBUTORS.rst
odoo/addons/account_move_line_tax_editable/readme/DESCRIPTION.rst
odoo/addons/account_move_line_tax_editable/static/description/icon.png
odoo/addons/account_move_line_tax_editable/static/description/index.html
odoo/addons/account_move_line_tax_editable/tests/__init__.py
odoo/addons/account_move_line_tax_editable/tests/test_account_move_line_tax_editable.py
odoo/addons/account_move_line_tax_editable/views/account_move.xml
odoo/addons/account_move_line_tax_editable/views/account_move_line.xml
odoo13_addon_account_move_line_tax_editable-13.0.2.0.0.dist-info/METADATA
odoo13_addon_account_move_line_tax_editable-13.0.2.0.0.dist-info/WHEEL
odoo13_addon_account_move_line_tax_editable-13.0.2.0.0.dist-info/top_level.txt
odoo13_addon_account_move_line_tax_editable-13.0.2.0.0.dist-info/RECORD
